django_nanopages/__init__.py
django_nanopages/nanodjango.py
django_nanopages/page.py
django_nanopages/pages.py
django_nanopages/views.py
django_nanopages/templates/django_nanopages/page.html
django_nanopages-0.3.1.dist-info/licenses/LICENSE.md
django_nanopages-0.3.1.dist-info/METADATA
django_nanopages-0.3.1.dist-info/WHEEL
django_nanopages-0.3.1.dist-info/entry_points.txt
django_nanopages-0.3.1.dist-info/top_level.txt
django_nanopages-0.3.1.dist-info/RECORD
