Metadata-Version: 2.4
Name: django-nanopages
Version: 0.3.1
Summary: Generate Django pages from Markdown, HTML, and Django template files.
Author-email: Richard Terry <code@radiac.net>
License-Expression: BSD-3-Clause
Project-URL: Homepage, https://radiac.net/projects/django-nanopages/
Project-URL: Documentation, https://django-nanopages.readthedocs.io/en/latest/
Project-URL: Changelog, https://django-nanopages.readthedocs.io/en/latest/changelog.html
Project-URL: Repository, https://github.com/radiac/django-nanopages
Project-URL: Issues, https://github.com/radiac/django-nanopages/issues
Keywords: django
Classifier: Development Status :: 4 - Beta
Classifier: Framework :: Django
Classifier: Programming Language :: Python :: 3
Classifier: Operating System :: OS Independent
Requires-Python: >=3.8
License-File: LICENSE.md
Requires-Dist: markdown
Provides-Extra: full
Requires-Dist: pyyaml; extra == "full"
Dynamic: license-file
